asphalt/sqlalchemy/__init__.py
asphalt/sqlalchemy/component.py
asphalt/sqlalchemy/py.typed
asphalt/sqlalchemy/utils.py
asphalt_sqlalchemy-5.1.0.dist-info/LICENSE
asphalt_sqlalchemy-5.1.0.dist-info/METADATA
asphalt_sqlalchemy-5.1.0.dist-info/WHEEL
asphalt_sqlalchemy-5.1.0.dist-info/entry_points.txt
asphalt_sqlalchemy-5.1.0.dist-info/top_level.txt
asphalt_sqlalchemy-5.1.0.dist-info/RECORD
